LICENSE
README.rst
setup.py
amepy/__init__.py
amepy/client.py
amepy/enums.py
amepy/errors.py
amepy/utils.py
amepy.egg-info/PKG-INFO
amepy.egg-info/SOURCES.txt
amepy.egg-info/dependency_links.txt
amepy.egg-info/requires.txt
amepy.egg-info/top_level.txt